Workbook
Name Slicer_Category: #N/A
Name Slicer_Category1: #N/A
Name Slicer_ExpenseType: #N/A
Name Slicer_ProductName: #N/A
Name Slicer_Supplier: #N/A
Name Slicer_Track_Stock: #N/A
Name Slicer_Unit: #N/A
Name Slicer_Unit1: #N/A

Sheet Sheet1
A1: Column1

Sheet Pivot_Tables
A4: Total_Sales_USD | B4: Total_Sales_AED | C4: Total_Expenses_USD | D4: Total_Expenses_AED | E4: COGS | F4: Gross_Profit | G4: Net_Profit | H4: Gross_Profit_Margin | I4: Net_Profit_Margin | J4: Avg_Selling_Price | K4: Total_Quantity_Sold | L4: Total_Quantity_Purchased
A5: 1699.2 | B5: 6247.0588 | C5: 2531 | D5: 9305.1471 | E5: 568.2125 | F5: 1130.9875 | G5: -1400.0125 | H5: 0.66559999 | I5: -0.55314599 | J5: 84.96 | K5: 20 | L5: 240
A8: Sales USD/AED Trends | E8: Gross_Profit vs Net_Profit | I8: Sales vs Expenses
A9: Row Labels | B9: Total_Sales_USD | C9: Total_Sales_AED | E9: Row Labels | F9: Gross_Profit | G9: Net_Profit | I9: Row Labels | J9: Total_Sales_USD | K9: Total_Expenses_USD
A10: October | E10: October | I10: October
A11: Sunday | B11: 299.2 | C11: 1100 | E11: Sunday | F11: 299.2 | G11: -220.8 | I11: Sunday | J11: 299.2 | K11: 520
A12: Monday | B12: 1400 | C12: 5147.0588 | E12: Monday | F12: 1400 | G12: 1400 | I12: Monday | J12: 1400
A13: Tuesday | B13: 0 | C13: 0 | E13: Tuesday | F13: 0 | G13: 0 | I13: Tuesday | J13: 0
A14: Grand Total | B14: 1699.2 | C14: 6247.0588 | E14: Wednesday | G14: -211 | I14: Wednesday | K14: 211
E15: Thursday | G15: -1300 | I15: Thursday | K15: 1300
E16: Friday | G16: -300 | I16: Friday | K16: 300
E17: Saturday | G17: -200 | I17: Saturday | K17: 200
E18: Grand Total | F18: 1130.9875 | G18: -1400.0125 | I18: Grand Total | J18: 1699.2 | K18: 2531
A20: Avg_Selling_Price Trends | D20: Product(Sales vs Gross_Profit)
A21: Row Labels | B21: Avg_Selling_Price | D21: Row Labels | E21: Total_Sales_USD | F21: Gross_Profit
A22: October | D22: Volcano | E22: 1400 | F22: 1115.8937
A23: Sunday | B23: 59.84 | D23: Azzurro | E23: 299.2 | F23: 15.09375
A24: Monday | B24: 140 | D24: Grand Total | E24: 1699.2 | F24: 1130.9875
A25: Tuesday | B25: 0
A26: Grand Total | B26: 84.96
A34: Avg_Purchase_Cost | B34: Active_Customers | C34: Active_Suppliers | D34: Shipping_Cost_Ratio | E34: Processing_Cost_Ratio | F34: Total_Purchases_USD | G34: Active_Suppliers | H34: Average_Expense | I34: Total_Operating_Expenses | J34: Operating_Expense_Ratio | K34: Avg_Purchase_Cost
A35: 28.410625 | B35: 3 | C35: 3 | D35: 0.025020073 | E35: 0.0077662523 | F35: 3689.038 | G35: 3 | H35: 361.57143 | I35: 2531 | J35: 1.4895245 | K35: 28.410625
A39: Purchases per Supplier | D39: Product Purchases | G39: Purchases Trend
A40: Row Labels | B40: Sum of Total_USD | D40: Row Labels | E40: Sum of Total_USD | G40: Row Labels | H40: Sum of Total_USD
A41: RPR-Coffee Roaster | B41: 2005.888 | D41: 1 | E41: 90.06 | G41: September
A42: Alibaba | B42: 1103.79 | D42: 2 | E42: 44 | G42: Tuesday | H42: 2005.888
A43: Wejar | B43: 579.36 | D43: 4 | E43: 50 | G43: Friday | H43: 1036.84
A44: Grand Total | B44: 3689.038 | D44: 5 | E44: 80 | G44: October
D45: 7 | E45: 120 | G45: Thursday | H45: 66.95
D46: 8 | E46: 70 | G46: Saturday | H46: 579.36
D47: Arabica | E47: 258.4 | G47: Grand Total | H47: 3689.038
D48: Azzurro | E48: 290
D49: Coffee Accessories | E49: 237.68
D50: Colmbine | E50: 144.16
D51: cup clear | E51: 32
D52: Eihiopian | E52: 176.8
D53: Png | E53: 230
D54: Shardor automatic flat burr coffee | E54: 313.1 | H54: Expenses Type Distribution
D55: small desktop | E55: 66.95 | H55: Row Labels | I55: Total_Expenses_USD
D56: Volcano | E56: 1485.888 | H56: Rent | I56: 211
D57: Grand Total | E57: 3689.038 | H57: Setup | I57: 2320
A58: Expenses Trend | H58: Grand Total | I58: 2531
A59: Row Labels | B59: Total_Expenses_USD
A60: October
A61: Sunday | B61: 520
A62: Wednesday | B62: 211
A63: Thursday | B63: 1300
A64: Friday | B64: 300 | D64: Top 5 Product Quantity Details
A65: Saturday | B65: 200 | D65: Coffee Accessories | E65: Purchases | F65: Quantity | G65: UnitPrice | H65: Shipping_Fee | I65: Processing_Fee
A66: Grand Total | B66: 2531 | D66: Volcano | E66: 1485.888 | F66: 100 | G66: 59.5 | H66: 20 | I66: 4
D67: Shardor automatic flat burr coffee | E67: 313.1 | F67: 8 | G67: 37 | H67: 8 | I67: 9.1
D68: Azzurro | E68: 290 | F68: 20 | G68: 14.5 | H68: 0 | I68: 0
D69: Arabica | E69: 258.4 | F69: 25 | G69: 38 | H69: 0 | I69: 0
D70: Coffee Accessories | E70: 237.68 | F70: 8 | G70: 26.23 | H70: 20 | I70: 7.84
D71: Grand Total | E71: 2585.068 | F71: 161 | G71: 175.23 | H71: 48 | I71: 20.94
A82: Total_Purchased_Inv | B82: Total_Sold_Inv | C82: Current_Stock_Total | D82: Inventory_Turnover | E82: Out_Of_Stock_Count | F82: Low_Stock_Count | G82: Normal_Stock_Count | H82: Out_Of_Stock_Percentage | I82: AED_to_USD | J82: USD_to_AED | K82: USD_to_IQD | L82: IQD_to_USD
A83: 225 | B83: 20 | C83: 205 | D83: 0.097560976 | E83: 9 | F83: 13 | G83: 1 | H83: 0.39130435 | I83: 0.272 | J83: 3.6764706 | K83: 1400 | L83: 0.00071428571
A86: Current Stock Status Distribution | D86: Top 10 Products Inv Details | I86: Currency Transaction Value
A87: Row Labels | B87: Sum of Current_Stock | D87: Row Labels | E87: Current_Stock | F87: Total_Sold | I87: Row Labels | J87: Sum of Value
A88: Low_Stock | B88: 115 | D88: Azzurro | E88: 10 | F88: 10 | I88: AED_to_USD | J88: 0.272
A89: Normal | B89: 90 | D89: Volcano | E89: 90 | F89: 10 | I89: USD_to_IQD | J89: 1400
A90: Grand Total | B90: 205 | D90: Eihiopian | E90: 10 | F90: 0 | I90: Grand Total | J90: 1400.272
D91: 6 | E91: 8 | F91: 0
D92: Colmbine | E92: 10 | F92: 0
D93: 7 | E93: 10 | F93: 0 | I93: Sales Currency Transaction
D94: Png | E94: 10 | F94: 0 | I94: Row Labels | J94: Sum of Quantity
D95: 8 | E95: 7 | F95: 0 | I95: USD_to_IQD | J95: 10
D96: 5 | E96: 8 | F96: 0 | I96: AED_to_USD | J96: 5
D97: Arabica | E97: 25 | F97: 0 | I97: Grand Total | J97: 15
D98: Grand Total | E98: 188 | F98: 20
A101: Out & Low Stock Category
A102: Row Labels | B102: Low_Stock_Count | C102: Out_Of_Stock_Count
A103: accessories | B103: 8
A104: Coffee | B104: 5 | C104: 9
A105: Grand Total | B105: 13 | C105: 9

Sheet Finance_Dashboard 

Sheet Operational_Dashboard
H19: =Pivot_Tables!D65 -> Coffee Accessories | I19: =Pivot_Tables!E65 -> Purchases | J19: =Pivot_Tables!F65 -> Quantity | K19: =Pivot_Tables!G65 -> UnitPrice | L19: =Pivot_Tables!H65 -> Shipping_Fee | M19: =Pivot_Tables!I65 -> Processing_Fee
H20: =Pivot_Tables!D66 -> Volcano | I20: =Pivot_Tables!E66 -> 1485.888 | J20: =Pivot_Tables!F66 -> 100 | K20: =Pivot_Tables!G66 -> 59.5 | L20: =Pivot_Tables!H66 -> 20 | M20: =Pivot_Tables!I66 -> 4
H21: =Pivot_Tables!D67 -> Shardor automatic flat burr coffee | I21: =Pivot_Tables!E67 -> 313.1 | J21: =Pivot_Tables!F67 -> 8 | K21: =Pivot_Tables!G67 -> 37 | L21: =Pivot_Tables!H67 -> 8 | M21: =Pivot_Tables!I67 -> 9.1
H22: =Pivot_Tables!D68 -> Azzurro | I22: =Pivot_Tables!E68 -> 290 | J22: =Pivot_Tables!F68 -> 20 | K22: =Pivot_Tables!G68 -> 14.5 | L22: =Pivot_Tables!H68 -> 0 | M22: =Pivot_Tables!I68 -> 0
H23: =Pivot_Tables!D69 -> Arabica | I23: =Pivot_Tables!E69 -> 258.4 | J23: =Pivot_Tables!F69 -> 25 | K23: =Pivot_Tables!G69 -> 38 | L23: =Pivot_Tables!H69 -> 0 | M23: =Pivot_Tables!I69 -> 0
H24: =Pivot_Tables!D70 -> Coffee Accessories | I24: =Pivot_Tables!E70 -> 237.68 | J24: =Pivot_Tables!F70 -> 8 | K24: =Pivot_Tables!G70 -> 26.23 | L24: =Pivot_Tables!H70 -> 20 | M24: =Pivot_Tables!I70 -> 7.84
H25: =Pivot_Tables!D71 -> Grand Total | I25: =Pivot_Tables!E71 -> 2585.068 | J25: =Pivot_Tables!F71 -> 161 | K25: =Pivot_Tables!G71 -> 175.23 | L25: =Pivot_Tables!H71 -> 48 | M25: =Pivot_Tables!I71 -> 20.94

Sheet Inventory&Cuurency_Dashboard 
B28: =Pivot_Tables!D87 -> Row Labels | C28: =Pivot_Tables!E87 -> Current_Stock | D28: =Pivot_Tables!F87 -> Total_Sold
B29: =Pivot_Tables!D88 -> Azzurro | C29: =Pivot_Tables!E88 -> 10 | D29: =Pivot_Tables!F88 -> 10
B30: =Pivot_Tables!D89 -> Volcano | C30: =Pivot_Tables!E89 -> 90 | D30: =Pivot_Tables!F89 -> 10
B31: =Pivot_Tables!D90 -> Eihiopian | C31: =Pivot_Tables!E90 -> 10 | D31: =Pivot_Tables!F90 -> 0
B32: =Pivot_Tables!D91 -> 6 | C32: =Pivot_Tables!E91 -> 8 | D32: =Pivot_Tables!F91 -> 0
B33: =Pivot_Tables!D92 -> Colmbine | C33: =Pivot_Tables!E92 -> 10 | D33: =Pivot_Tables!F92 -> 0
B34: =Pivot_Tables!D93 -> 7 | C34: =Pivot_Tables!E93 -> 10 | D34: =Pivot_Tables!F93 -> 0
B35: =Pivot_Tables!D94 -> Png | C35: =Pivot_Tables!E94 -> 10 | D35: =Pivot_Tables!F94 -> 0
B36: =Pivot_Tables!D95 -> 8 | C36: =Pivot_Tables!E95 -> 7 | D36: =Pivot_Tables!F95 -> 0
B37: =Pivot_Tables!D96 -> 5 | C37: =Pivot_Tables!E96 -> 8 | D37: =Pivot_Tables!F96 -> 0
B38: =Pivot_Tables!D97 -> Arabica | C38: =Pivot_Tables!E97 -> 25 | D38: =Pivot_Tables!F97 -> 0
B39: =Pivot_Tables!D98 -> Grand Total | C39: =Pivot_Tables!E98 -> 188 | D39: =Pivot_Tables!F98 -> 20
